napari_fast4dreg/__init__.py
napari_fast4dreg/_fast4Dreg_functions.py
napari_fast4dreg/_widget.py
napari_fast4dreg/napari.yaml
napari_fast4dreg/_tests/__init__.py
napari_fast4dreg/_tests/test_widget.py
napari_fast4dreg-0.0.1.dist-info/LICENSE
napari_fast4dreg-0.0.1.dist-info/METADATA
napari_fast4dreg-0.0.1.dist-info/WHEEL
napari_fast4dreg-0.0.1.dist-info/entry_points.txt
napari_fast4dreg-0.0.1.dist-info/top_level.txt
napari_fast4dreg-0.0.1.dist-info/RECORD
